odoo/addons/l10n_de_country_states/README.rst
odoo/addons/l10n_de_country_states/__init__.py
odoo/addons/l10n_de_country_states/__manifest__.py
odoo/addons/l10n_de_country_states/data/res_country_states.xml
odoo/addons/l10n_de_country_states/i18n/de.po
odoo/addons/l10n_de_country_states/i18n/l10n_de_country_states.pot
odoo/addons/l10n_de_country_states/readme/CONTRIBUTORS.rst
odoo/addons/l10n_de_country_states/readme/DESCRIPTION.rst
odoo/addons/l10n_de_country_states/readme/INSTALL.rst
odoo/addons/l10n_de_country_states/static/description/icon.png
odoo/addons/l10n_de_country_states/static/description/index.html
odoo13_addon_l10n_de_country_states-13.0.1.0.1.dev3.dist-info/METADATA
odoo13_addon_l10n_de_country_states-13.0.1.0.1.dev3.dist-info/WHEEL
odoo13_addon_l10n_de_country_states-13.0.1.0.1.dev3.dist-info/top_level.txt
odoo13_addon_l10n_de_country_states-13.0.1.0.1.dev3.dist-info/RECORD
